{
    "users_store": {
        "1": {
            "id": 1,
            "username": "admin",
            "name": "Admin User",
            "password": "password",
            "is_admin": true
        },
        "2": {
            "id": 2,
            "username": "Gloria",
            "name": "Gloria Walumbe",
            "password": "Walumbe2.",
            "is_admin": false
        },
        "3": {
            "id": 3,
            "username": "Christa",
            "name": "Christabel Walumbe",
            "password": "Walumbe1.",
            "is_admin": true
        }
    },
    "next_user_id": 4,
    "jobs_store": {
        "101": {
            "id": 101,
            "title": "Alarm installer",
            "description": "install the alarm at peponi road gate number 123",
            "status": "DONE",
            "assignedToId": 2
        }
    },
    "next_job_id": 102
}